{
  "name": "vsystem-web",
  "alias": "vsystem-web.now.sh",
  "env": {
    "HOST": "127.0.0.1",
    "PORT": "3333",
    "NODE_ENV": "development",
    "APP_NAME": "vsystem-web",
    "APP_URL": "http://${HOST}:${PORT}",
    "APP_KEY": "VWS8KPOh3uIurDvpzZBr88xZuIcYResr",
    "HASH_DRIVER": "bcrypt",
    "DB_CONNECTION": "mongodb",
    "MONGO_CONNECTION_STRING": "mongodb://eco:asd123@ds151453.mlab.com:51453/vsystem-web",
    "OMONGO_HOST": " ds151453.mlab.com",
    "OMONGO_PORT": "51453",
    "OMONGO_USER": "eco",
    "OMONGO_PASSWORD": "asd123",
    "OMONGO_DATABASE": "vsystem-web"
  }
}
